01_rtl/PISO.sv
module PISO #(
    parameter SIZE_DATA_IN = 16,
    parameter SIZE_DATA_OUT = 2
)(
    input logic i_clk,
    input logic i_rst_n,
    input logic i_start,
    input logic [SIZE_DATA_IN-1:0] i_data,
    output logic [SIZE_DATA_OUT-1:0] o_data,
    output logic o_valid,
    output logic o_done
);

parameter DEPTH = SIZE_DATA_IN / SIZE_DATA_OUT;
parameter SIZE_DEPTH = $clog2(DEPTH);
logic [SIZE_DATA_OUT-1:0] shift_reg [0:DEPTH-1];

// Setup counter
logic [SIZE_DEPTH-1:0] count, ncount;
logic w_update_count;
logic w_count, w_count_next;
assign w_update_count = i_start & (~o_done);
assign w_count_next = w_update_count & w_count;
assign ncount = w_count_next ? count + 1'b1 : '0;
always_ff @(posedge i_clk or negedge i_rst_n) begin : proc_count
    if(~i_rst_n) begin
        count   <= '0;
        w_count <= 1'b0;
    end else begin
        count   <= ncount;
        w_count <= w_update_count;
    end
end

// Setup shift register
logic [SIZE_DATA_IN-1:0] w_idata;
logic [SIZE_DATA_IN-1:0] w_idata_next; 
logic w_update_idata;
assign w_update_idata = i_start & (~w_count_next);
assign w_idata = w_update_idata ? i_data : w_idata_next;
always_ff @( posedge i_clk or negedge i_rst_n ) begin : save_w_idata
    if(~i_rst_n) begin
        w_idata_next <= '0;
    end else begin
        w_idata_next <= w_idata;
    end
end
always_comb begin : proc_shift_reg
    shift_reg[0] = w_idata[1:0];
    shift_reg[1] = w_idata[3:2];
    shift_reg[2] = w_idata[5:4];
    shift_reg[3] = w_idata[7:6];
    shift_reg[4] = w_idata[9:8];
    shift_reg[5] = w_idata[11:10];
    shift_reg[6] = w_idata[13:12];
    shift_reg[7] = w_idata[15:14];
end

// Setup output data
logic [SIZE_DATA_OUT-1:0] w_output;
// logic w_valid;
always_ff @(posedge i_clk or negedge i_rst_n) begin : proc_outut_data
    if(~i_rst_n) begin
        w_output <= '0;
    end else begin
        // if(w_update_count) begin
        //     w_output <= shift_reg[count];
        //     w_valid <= 1'b1; 
        // end else begin
        //     w_output <= '0;
        //     w_valid <= 1'b0;
        // end
        w_output <= shift_reg[count];
    end
end
// assign o_data = w_count_next ? w_output : '0;
assign o_data = o_valid ? w_output : '0;
// assign o_data = o_valid & w_output;

// Setup Output valid signal
wire w_ovalid;
assign w_ovalid = w_count_next;
// assign w_ovalid = w_count_next ? 1'b1 : 1'b0;
always_ff @( posedge i_clk or negedge i_rst_n ) begin : proc_valid
    if(~i_rst_n) begin
        o_valid <= 1'b0;
    end else begin
        o_valid <= w_ovalid;
    end
end
// Setup Output done signal
logic w_done;
assign w_done = &count;
always_ff @(posedge i_clk or negedge i_rst_n) begin : proc_done
    if(~i_rst_n) begin
        o_done <= 1'b0;
    end else begin
        o_done <= w_done;
    end
end

endmodule

02_verif/tb_PISO.sv
`timescale 1ns/1ps
module tb_PISO;

  parameter SIZE_DATA_IN = 16;
  parameter SIZE_DATA_OUT = 2;

  logic i_clk, i_rst_n, i_start;
  logic [SIZE_DATA_IN-1:0] i_data;
  logic [SIZE_DATA_OUT-1:0] o_data;
  logic o_valid, o_done;

  // Clock generation
  always #10 i_clk = ~i_clk;

  // Instantiate the PISO module
  PISO #(
      .SIZE_DATA_IN (SIZE_DATA_IN),
      .SIZE_DATA_OUT(SIZE_DATA_OUT)
  ) uut (
      .i_clk      (i_clk),
      .i_rst_n    (i_rst_n),
      .i_start    (i_start),
      .i_data     (i_data),
      .o_data     (o_data),
      .o_valid    (o_valid),
      .o_done     (o_done)
  );

  // VCD dump for waveform analysis
  initial begin
      $dumpfile("tb_PISO.vcd");
      $dumpvars(0, tb_PISO);
  end

  // Task to display signals
  task display_signals;
      $display("Time = %t \t| i_start = %b \t| i_data = %b \t| o_data = %b \t| o_valid = %b \t| o_done = %b",
               $time, i_start, i_data, o_data, o_valid, o_done);
  endtask

  // Task to run a test case with given inputs
  task run_test_case(input string test_name, logic rst_n, logic start, logic [SIZE_DATA_IN-1:0] data, integer cycles);
      $display("========== %s =========", test_name);
      i_rst_n = rst_n;
      i_start = start;
      i_data = data;
      #20; // Wait for signal stabilization
      if (!rst_n) begin
          #20;
          i_rst_n = 1'b1; // Release reset if needed
      end
      repeat (cycles) begin
          @(posedge i_clk);
          display_signals();
          if (o_done) begin
              $display("Done processing data.");
              @(posedge i_clk);
              break; // Exit loop when done
          end
      end
  endtask

  // Main test sequence
  initial begin
      // Initialize signals
      i_clk = 1'b0;
      i_rst_n = 1'b0;
      i_start = 1'b0;
      i_data = 16'h0000;

      // Test Case 1: Reset and Start
      run_test_case("Test Case 1: Reset and Start", 1'b0, 1'b0, 16'h1234, 10);

      #100; // Inter-test delay

      // Test Case 2: Test Output After Reset
      run_test_case("Test Case 2: Test Output After Reset", 1'b0, 1'b1, 16'h1234, 10);

      #100; // Inter-test delay

      // Test Case 3: Change Data When Start is High
      run_test_case("Test Case 3: Change Data When Start is High - Data = 0x1234", 1'b0, 1'b1, 16'h1234, 2);
      run_test_case("Test Case 3: Change Data When Start is High - Data = 0x5678", 1'b1, 1'b1, 16'h5678, 8);
      
      #100; // Inter-test delay

      // Test Case 4: Change Start Signal While Data is Being Processed
      $display("========== Test Case 4: Change Start Signal While Data is Being Processed =========");
      i_start = 1'b0;
      #20;
      i_start = 1'b1;
      i_data = 16'h5678;
      repeat (5) begin
          @(posedge i_clk);
          display_signals();
          if (o_done) begin
              $display("Done processing new data.");
              @(posedge i_clk);
              break;
          end
      end
      i_start = 1'b0;
      repeat (5) begin
          @(posedge i_clk);
          display_signals();
          if (o_done) begin
              $display("Done processing new data.");
              @(posedge i_clk);
              break;
          end
      end
      
      #100;

      // Finish simulation
      $display("Simulation completed.");
      $finish;
  end

endmodule

02_verif/tb_PISO.vcd
$version Generated by VerilatedVcd $end
$timescale 1ps $end
 $scope module TOP $end
  $scope module tb_PISO $end
   $var wire 32 < SIZE_DATA_IN [31:0] $end
   $var wire 32 = SIZE_DATA_OUT [31:0] $end
   $var wire 1 6 i_clk $end
   $var wire 1 7 i_rst_n $end
   $var wire 1 8 i_start $end
   $var wire 16 9 i_data [15:0] $end
   $var wire 2 . o_data [1:0] $end
   $var wire 1 / o_valid $end
   $var wire 1 0 o_done $end
   $scope module uut $end
    $var wire 32 < SIZE_DATA_IN [31:0] $end
    $var wire 32 = SIZE_DATA_OUT [31:0] $end
    $var wire 1 6 i_clk $end
    $var wire 1 7 i_rst_n $end
    $var wire 1 8 i_start $end
    $var wire 16 9 i_data [15:0] $end
    $var wire 2 . o_data [1:0] $end
    $var wire 1 / o_valid $end
    $var wire 1 0 o_done $end
    $var wire 32 > DEPTH [31:0] $end
    $var wire 32 ? SIZE_DEPTH [31:0] $end
    $var wire 2 # shift_reg[0] [1:0] $end
    $var wire 2 $ shift_reg[1] [1:0] $end
    $var wire 2 % shift_reg[2] [1:0] $end
    $var wire 2 & shift_reg[3] [1:0] $end
    $var wire 2 ' shift_reg[4] [1:0] $end
    $var wire 2 ( shift_reg[5] [1:0] $end
    $var wire 2 ) shift_reg[6] [1:0] $end
    $var wire 2 * shift_reg[7] [1:0] $end
    $var wire 3 1 count [2:0] $end
    $var wire 3 : ncount [2:0] $end
    $var wire 1 + w_update_count $end
    $var wire 1 2 w_count $end
    $var wire 1 , w_count_next $end
    $var wire 16 - w_idata [15:0] $end
    $var wire 16 3 w_idata_next [15:0] $end
    $var wire 1 ; w_update_idata $end
    $var wire 2 4 w_output [1:0] $end
    $var wire 1 , w_ovalid $end
    $var wire 1 5 w_done $end
   $upscope $end
  $upscope $end
 $upscope $end
$enddefinitions $end


#0
b00 #
b00 $
b00 %
b00 &
b00 '
b00 (
b00 )
b00 *
0+
0,
b0000000000000000 -
b00 .
0/
00
b000 1
02
b0000000000000000 3
b00 4
05
06
07
08
b0001001000110100 9
b000 :
0;
b00000000000000000000000000010000 <
b00000000000000000000000000000010 =
b00000000000000000000000000001000 >
b00000000000000000000000000000011 ?
#10000
16
#20000
06
#30000
16
#40000
06
17
#50000
16
#60000
06
#70000
16
#80000
06
#90000
16
#100000
06
#110000
16
#120000
06
#130000
16
#140000
06
#150000
16
#160000
06
#170000
16
#180000
06
#190000
16
#200000
06
#210000
16
#220000
06
#230000
16
#240000
06
#250000
16
#260000
06
#270000
16
#280000
06
#290000
16
#300000
06
#310000
16
#320000
06
#330000
b01 $
b11 %
b10 '
b01 )
1+
b0001001000110100 -
16
07
18
1;
#340000
06
#350000
16
#360000
06
#370000
1,
12
b0001001000110100 3
16
17
b001 :
0;
#380000
06
#390000
1/
b001 1
16
b010 :
#400000
06
#410000
b01 .
b010 1
b01 4
16
b011 :
#420000
06
#430000
b11 .
b011 1
b11 4
16
b100 :
#440000
06
#450000
b00 .
b100 1
b00 4
16
b101 :
#460000
06
#470000
b10 .
b101 1
b10 4
16
b110 :
#480000
06
#490000
b00 .
b110 1
b00 4
16
b111 :
#500000
06
#510000
b01 .
b111 1
b01 4
15
16
b000 :
#520000
06
#530000
0+
0,
b00 .
10
b000 1
b00 4
05
16
1;
#540000
06
#550000
1+
0/
00
02
16
#560000
06
#570000
1,
12
16
b001 :
0;
#580000
06
#590000
1/
b001 1
16
b010 :
#600000
06
#610000
b01 .
b010 1
b01 4
16
b011 :
#620000
06
#630000
b11 .
b011 1
b11 4
16
b100 :
#640000
06
#650000
b00 .
b100 1
b00 4
16
b101 :
#660000
06
#670000
0,
0/
b000 1
02
b0000000000000000 3
16
07
b000 :
1;
#680000
06
#690000
16
#700000
06
#710000
1,
12
b0001001000110100 3
16
17
b001 :
0;
#720000
06
#730000
1/
b001 1
16
b010 :
#740000
06
#750000
b01 .
b010 1
b01 4
16
b0101011001111000 9
b011 :
#760000
06
#770000
b11 .
b011 1
b11 4
16
b100 :
#780000
06
#790000
b00 .
b100 1
b00 4
16
b101 :
#800000
06
#810000
b10 .
b101 1
b10 4
16
b110 :
#820000
06
#830000
b00 .
b110 1
b00 4
16
b111 :
#840000
06
#850000
b01 .
b111 1
b01 4
15
16
b000 :
#860000
06
#870000
b10 $
b01 &
b01 (
b01 *
0+
0,
b0101011001111000 -
b00 .
10
b000 1
b00 4
05
16
1;
#880000
06
#890000
1+
0/
00
02
b0101011001111000 3
16
#900000
06
#910000
1,
12
16
b001 :
0;
#920000
06
#930000
1/
b001 1
16
b010 :
#940000
06
#950000
b10 .
b010 1
b10 4
16
b011 :
#960000
06
#970000
b11 .
b011 1
b11 4
16
b100 :
#980000
06
#990000
b01 .
b100 1
b01 4
16
b101 :
#1000000
06
#1010000
0+
0,
b00 .
0/
b000 1
02
b10 4
16
08
b000 :
#1020000
06
#1030000
1+
1,
12
b00 4
16
18
b001 :
#1040000
06
#1050000
1/
b001 1
16
b010 :
#1060000
06
#1070000
b10 .
b010 1
b10 4
16
b011 :
#1080000
06
#1090000
b11 .
b011 1
b11 4
16
b100 :
#1100000
06
#1110000
b01 .
b100 1
b01 4
16
b101 :
#1120000
06
#1130000
0+
0,
b00 .
0/
b000 1
02
b10 4
16
08
b000 :
#1140000
06
#1150000
b00 4
16
