01_rtl/PISO.sv
module PISO #(
    parameter SIZE_DATA_IN = 16,
    parameter SIZE_DATA_OUT = 2
)(
    input logic i_clk,
    input logic i_rst_n,
    input logic i_start,
    input logic [SIZE_DATA_IN-1:0] i_data,
    output logic [SIZE_DATA_OUT-1:0] o_data,
    output logic o_valid,
    output logic o_done
);

parameter DEPTH = SIZE_DATA_IN / SIZE_DATA_OUT;
parameter SIZE_DEPTH = $clog2(DEPTH);
logic [SIZE_DATA_OUT-1:0] shift_reg [0:DEPTH-1];

// Setup counter
logic [SIZE_DEPTH-1:0] count, ncount;
logic w_update_count;
logic w_count, w_count_next;
assign w_update_count = i_start & (~o_done);
assign w_count_next = w_update_count & w_count;
assign ncount = w_count_next ? count + 1'b1 : '0;
always_ff @(posedge i_clk or negedge i_rst_n) begin : proc_count
    if(~i_rst_n) begin
        count   <= '0;
        w_count <= 1'b0;
    end else begin
        count   <= ncount;
        w_count <= w_update_count;
    end
end

// Setup shift register
logic [SIZE_DATA_IN-1:0] w_idata, w_idata_next; 
logic w_update_idata;
assign w_update_idata = i_start & (~w_count_next);
assign w_idata = w_update_idata ? i_data : w_idata_next;
assign w_idata_next = w_idata;
always_comb begin : proc_shift_reg
    shift_reg[0] = w_idata[1:0];
    shift_reg[1] = w_idata[3:2];
    shift_reg[2] = w_idata[5:4];
    shift_reg[3] = w_idata[7:6];
    shift_reg[4] = w_idata[9:8];
    shift_reg[5] = w_idata[11:10];
    shift_reg[6] = w_idata[13:12];
    shift_reg[7] = w_idata[15:14];
end

// Setup output data
logic [SIZE_DATA_OUT-1:0] w_output;
// logic w_valid;
always_ff @(posedge i_clk or negedge i_rst_n) begin : proc_outut_data
    if(~i_rst_n) begin
        w_output <= '0;
    end else begin
        // if(w_update_count) begin
        //     w_output <= shift_reg[count];
        //     w_valid <= 1'b1; 
        // end else begin
        //     w_output <= '0;
        //     w_valid <= 1'b0;
        // end
        w_output <= shift_reg[count];
    end
end
// assign o_data = w_count_next ? w_output : '0;
assign o_data = o_valid ? w_output : '0;
// assign o_data = o_valid & w_output;

// Setup Output valid signal
wire w_ovalid;
assign w_ovalid = w_count_next;
// assign w_ovalid = w_count_next ? 1'b1 : 1'b0;
always_ff @( posedge i_clk or negedge i_rst_n ) begin : proc_valid
    if(~i_rst_n) begin
        o_valid <= 1'b0;
    end else begin
        o_valid <= w_ovalid;
    end
end
// Setup Output done signal
logic w_done;
assign w_done = &count;
always_ff @(posedge i_clk or negedge i_rst_n) begin : proc_done
    if(~i_rst_n) begin
        o_done <= 1'b0;
    end else begin
        o_done <= w_done;
    end
end

endmodule

02_verif/tb_PISO.sv
`timescale 1ns/1ps
module tb_PISO;

  parameter SIZE_DATA_IN = 16;
  parameter SIZE_DATA_OUT = 2;

  logic i_clk, i_rst_n, i_start;
  logic [SIZE_DATA_IN-1:0] i_data;
  logic [SIZE_DATA_OUT-1:0] o_data;
  logic o_valid, o_done;

  // Clock generation
  always #10 i_clk = ~i_clk;

  // Instantiate the PISO module
  PISO #(
      .SIZE_DATA_IN (SIZE_DATA_IN),
      .SIZE_DATA_OUT(SIZE_DATA_OUT)
  ) uut (
      .i_clk      (i_clk),
      .i_rst_n    (i_rst_n),
      .i_start    (i_start),
      .i_data     (i_data),
      .o_data     (o_data),
      .o_valid    (o_valid),
      .o_done     (o_done)
  );

  // VCD dump for waveform analysis
  initial begin
      $dumpfile("tb_PISO.vcd");
      $dumpvars(0, tb_PISO);
  end

  // Task to display signals
  task display_signals;
      $display("Time = %t \t| i_start = %b \t| i_data = %b \t| o_data = %b \t| o_valid = %b \t| o_done = %b",
               $time, i_start, i_data, o_data, o_valid, o_done);
  endtask

  // Task to run a test case with given inputs
  task run_test_case(input string test_name, logic rst_n, logic start, logic [SIZE_DATA_IN-1:0] data, integer cycles);
      $display("========== %s =========", test_name);
      i_rst_n = rst_n;
      i_start = start;
      i_data = data;
      #20; // Wait for signal stabilization
      if (!rst_n) begin
          #20;
          i_rst_n = 1'b1; // Release reset if needed
      end
      repeat (cycles) begin
          @(posedge i_clk);
          display_signals();
          if (o_done) begin
              $display("Done processing data.");
              @(posedge i_clk);
              break; // Exit loop when done
          end
      end
  endtask

  // Main test sequence
  initial begin
      // Initialize signals
      i_clk = 1'b0;
      i_rst_n = 1'b0;
      i_start = 1'b0;
      i_data = 16'h0000;

      // Test Case 1: Reset and Start
      run_test_case("Test Case 1: Reset and Start", 1'b0, 1'b0, 16'h1234, 10);

      #100; // Inter-test delay

      // Test Case 2: Test Output After Reset
      run_test_case("Test Case 2: Test Output After Reset", 1'b0, 1'b1, 16'h1234, 10);

      #100; // Inter-test delay

      // Test Case 3: Change Data When Start is High
      run_test_case("Test Case 3: Change Data When Start is High - Data = 0x1234", 1'b0, 1'b1, 16'h1234, 2);
      run_test_case("Test Case 3: Change Data When Start is High - Data = 0x5678", 1'b1, 1'b1, 16'h5678, 8);
      
      #100; // Inter-test delay

      // Test Case 4: Change Start Signal While Data is Being Processed
      $display("========== Test Case 4: Change Start Signal While Data is Being Processed =========");
      i_start = 1'b0;
      #20;
      i_start = 1'b1;
      i_data = 16'h5678;
      repeat (5) begin
          @(posedge i_clk);
          display_signals();
          if (o_done) begin
              $display("Done processing new data.");
              @(posedge i_clk);
              break;
          end
      end
      i_start = 1'b0;
      repeat (5) begin
          @(posedge i_clk);
          display_signals();
          if (o_done) begin
              $display("Done processing new data.");
              @(posedge i_clk);
              break;
          end
      end
      
      #100;

      // Finish simulation
      $display("Simulation completed.");
      $finish;
  end

endmodule

02_verif/tb_PISO.vcd
$version Generated by VerilatedVcd $end
$timescale 1ps $end
 $scope module TOP $end
  $scope module tb_PISO $end
   $var wire 32 ; SIZE_DATA_IN [31:0] $end
   $var wire 32 < SIZE_DATA_OUT [31:0] $end
   $var wire 1 3 i_clk $end
   $var wire 1 4 i_rst_n $end
   $var wire 1 5 i_start $end
   $var wire 16 6 i_data [15:0] $end
   $var wire 2 , o_data [1:0] $end
   $var wire 1 - o_valid $end
   $var wire 1 . o_done $end
   $scope module uut $end
    $var wire 32 ; SIZE_DATA_IN [31:0] $end
    $var wire 32 < SIZE_DATA_OUT [31:0] $end
    $var wire 1 3 i_clk $end
    $var wire 1 4 i_rst_n $end
    $var wire 1 5 i_start $end
    $var wire 16 6 i_data [15:0] $end
    $var wire 2 , o_data [1:0] $end
    $var wire 1 - o_valid $end
    $var wire 1 . o_done $end
    $var wire 32 = DEPTH [31:0] $end
    $var wire 32 > SIZE_DEPTH [31:0] $end
    $var wire 2 # shift_reg[0] [1:0] $end
    $var wire 2 $ shift_reg[1] [1:0] $end
    $var wire 2 % shift_reg[2] [1:0] $end
    $var wire 2 & shift_reg[3] [1:0] $end
    $var wire 2 ' shift_reg[4] [1:0] $end
    $var wire 2 ( shift_reg[5] [1:0] $end
    $var wire 2 ) shift_reg[6] [1:0] $end
    $var wire 2 * shift_reg[7] [1:0] $end
    $var wire 3 / count [2:0] $end
    $var wire 3 7 ncount [2:0] $end
    $var wire 1 8 w_update_count $end
    $var wire 1 0 w_count $end
    $var wire 1 9 w_count_next $end
    $var wire 16 + w_idata [15:0] $end
    $var wire 16 + w_idata_next [15:0] $end
    $var wire 1 : w_update_idata $end
    $var wire 2 1 w_output [1:0] $end
    $var wire 1 9 w_ovalid $end
    $var wire 1 2 w_done $end
   $upscope $end
  $upscope $end
 $upscope $end
$enddefinitions $end


#0
b00 #
b00 $
b00 %
b00 &
b00 '
b00 (
b00 )
b00 *
b0000000000000000 +
b00 ,
0-
0.
b000 /
00
b00 1
02
03
04
05
b0001001000110100 6
b000 7
08
09
0:
b00000000000000000000000000010000 ;
b00000000000000000000000000000010 <
b00000000000000000000000000001000 =
b00000000000000000000000000000011 >
#10000
13
#20000
03
#30000
13
#40000
03
14
#50000
13
#60000
03
#70000
13
#80000
03
#90000
13
#100000
03
#110000
13
#120000
03
#130000
13
#140000
03
#150000
13
#160000
03
#170000
13
#180000
03
#190000
13
#200000
03
#210000
13
#220000
03
#230000
13
#240000
03
#250000
13
#260000
03
#270000
13
#280000
03
#290000
13
#300000
03
#310000
13
#320000
03
#330000
b01 $
b11 %
b10 '
b01 )
b0001001000110100 +
13
04
15
18
1:
#340000
03
#350000
13
#360000
03
#370000
10
13
14
b001 7
19
0:
#380000
03
#390000
1-
b001 /
13
b010 7
#400000
03
#410000
b01 ,
b010 /
b01 1
13
b011 7
#420000
03
#430000
b11 ,
b011 /
b11 1
13
b100 7
#440000
03
#450000
b00 ,
b100 /
b00 1
13
b101 7
#460000
03
#470000
b10 ,
b101 /
b10 1
13
b110 7
#480000
03
#490000
b00 ,
b110 /
b00 1
13
b111 7
#500000
03
#510000
b01 ,
b111 /
b01 1
12
13
b000 7
#520000
03
#530000
b00 ,
1.
b000 /
b00 1
02
13
08
09
1:
#540000
03
#550000
0-
0.
00
13
18
#560000
03
#570000
10
13
b001 7
19
0:
#580000
03
#590000
1-
b001 /
13
b010 7
#600000
03
#610000
b01 ,
b010 /
b01 1
13
b011 7
#620000
03
#630000
b11 ,
b011 /
b11 1
13
b100 7
#640000
03
#650000
b00 ,
b100 /
b00 1
13
b101 7
#660000
03
#670000
0-
b000 /
00
13
04
b000 7
09
1:
#680000
03
#690000
13
#700000
03
#710000
10
13
14
b001 7
19
0:
#720000
03
#730000
1-
b001 /
13
b010 7
#740000
03
#750000
b01 ,
b010 /
b01 1
13
b0101011001111000 6
b011 7
#760000
03
#770000
b11 ,
b011 /
b11 1
13
b100 7
#780000
03
#790000
b00 ,
b100 /
b00 1
13
b101 7
#800000
03
#810000
b10 ,
b101 /
b10 1
13
b110 7
#820000
03
#830000
b00 ,
b110 /
b00 1
13
b111 7
#840000
03
#850000
b01 ,
b111 /
b01 1
12
13
b000 7
#860000
03
#870000
b10 $
b01 &
b01 (
b01 *
b0101011001111000 +
b00 ,
1.
b000 /
b00 1
02
13
08
09
1:
#880000
03
#890000
0-
0.
00
13
18
#900000
03
#910000
10
13
b001 7
19
0:
#920000
03
#930000
1-
b001 /
13
b010 7
#940000
03
#950000
b10 ,
b010 /
b10 1
13
b011 7
#960000
03
#970000
b11 ,
b011 /
b11 1
13
b100 7
#980000
03
#990000
b01 ,
b100 /
b01 1
13
b101 7
#1000000
03
#1010000
b00 ,
0-
b000 /
00
b10 1
13
05
b000 7
08
09
#1020000
03
#1030000
10
b00 1
13
15
b001 7
18
19
#1040000
03
#1050000
1-
b001 /
13
b010 7
#1060000
03
#1070000
b10 ,
b010 /
b10 1
13
b011 7
#1080000
03
#1090000
b11 ,
b011 /
b11 1
13
b100 7
#1100000
03
#1110000
b01 ,
b100 /
b01 1
13
b101 7
#1120000
03
#1130000
b00 ,
0-
b000 /
00
b10 1
13
05
b000 7
08
09
#1140000
03
#1150000
b00 1
13
